setup.cfg
setup.py
xcom2modsync/__init__.py
xcom2modsync/__main__.py
xcom2modsync/command.py
xcom2modsync/constants.py
xcom2modsync/exceptions.py
xcom2modsync/synchronizer.py
xcom2modsync.egg-info/PKG-INFO
xcom2modsync.egg-info/SOURCES.txt
xcom2modsync.egg-info/dependency_links.txt
xcom2modsync.egg-info/entry_points.txt
xcom2modsync.egg-info/requires.txt
xcom2modsync.egg-info/top_level.txt