Metadata-Version: 1.1
Name: xcom2modsync
Version: 1.0.0
Summary: Install Steam Workshop mods into XCOM2 mod directory.
Home-page: https://gitlab.com/nCrazed/XCOM2-Mod-Synchronizer
Author: Edvin Malinovskis
Author-email: github@edvin.io
License: MIT
Download-URL: https://gitlab.com/nCrazed/XCOM2-Mod-Synchronizer/repository/archive.tar.gz?ref=1.0.0
Keywords: xcom2,mods
Platform: UNKNOWN
